crspy/__init__.py
crspy/additional_metadata.py
crspy/era5_land.py
crspy/full_process_wrapper.py
crspy/gen_funcs.py
crspy/graphical_functions.py
crspy/initial_setup.py
crspy/mass_atten.py
crspy/n0_calibration.py
crspy/neutron_coeff_creation.py
crspy/neutron_correction_funcs.py
crspy/qa.py
crspy/theta.py
crspy/tidy_data.py
crspy-1.3.dist-info/LICENSE
crspy-1.3.dist-info/METADATA
crspy-1.3.dist-info/WHEEL
crspy-1.3.dist-info/top_level.txt
crspy-1.3.dist-info/RECORD
