Metadata-Version: 2.1
Name: crspy
Version: 1.3
Summary: Toolbox for calibration and correction of Cosmic Ray Neutron Sensor data using globally available data sources
Author: Daniel Power
Author-email: daniel.power@bristol.ac.uk
License-File: LICENSE
Requires-Dist: numpy (==1.22.0)
Requires-Dist: pandas (==1.3.2)
Requires-Dist: matplotlib (==3.4.3)
Requires-Dist: seaborn (==0.11.2)
Requires-Dist: cdsapi (==0.5.1)
Requires-Dist: xarray (==0.19.0)
Requires-Dist: scipy (==1.7)
Requires-Dist: netCDF4 (==1.5.7)
Requires-Dist: beautifulsoup4 (==4.9.3)
Requires-Dist: ipykernel
Requires-Dist: ipython
